lao_text_evaluation/__init__.py
lao_text_evaluation/cli.py
lao_text_evaluation/config.py
lao_text_evaluation/metrics.py
lao_text_evaluation/plotting.py
lao_text_evaluation/utils.py
lao_text_evaluation-0.2.1.dist-info/METADATA
lao_text_evaluation-0.2.1.dist-info/WHEEL
lao_text_evaluation-0.2.1.dist-info/entry_points.txt
lao_text_evaluation-0.2.1.dist-info/top_level.txt
lao_text_evaluation-0.2.1.dist-info/RECORD
