Metadata-Version: 2.1
Name: lao-text-evaluation
Version: 0.2.1
Summary: Lao OCR Evaluation Tool with CER/WER and visual alignment
Author: Khonepaseuth SOUNAKHEN
Author-email: Khonepaseuth SOUNAKHEN <khonepaserth.snk14@gmail.com>
License: MIT
Requires-Python: >=3.7
Requires-Dist: matplotlib
Requires-Dist: regex
Requires-Dist: numpy
